marquez_airflow/__init__.py
marquez_airflow/dag.py
marquez_airflow-0.20.0.dist-info/METADATA
marquez_airflow-0.20.0.dist-info/WHEEL
marquez_airflow-0.20.0.dist-info/top_level.txt
marquez_airflow-0.20.0.dist-info/RECORD
