Metadata-Version: 2.1
Name: marquez-airflow
Version: 0.20.0
Summary: Marquez integration with Airflow
Home-page: UNKNOWN
Author: Marquez Project
License: UNKNOWN
Keywords: marquez
Platform: UNKNOWN
Requires-Python: >=3.6
Requires-Dist: openlineage-airflow (==0.3.1)
